geowatch/__init__.py
geowatch/__main__.py
geowatch/exceptions.py
geowatch/heuristics.py
geowatch/cli/__init__.py
geowatch/cli/__main__.py
geowatch/cli/animate_visualizations.py
geowatch/cli/baseline_framework_ingress.py
geowatch/cli/cluster_sites.py
geowatch/cli/coco_add_ignore_buffer.py
geowatch/cli/coco_add_watch_fields.py
geowatch/cli/coco_align.py
geowatch/cli/coco_average_features.py
geowatch/cli/coco_clean_geotiffs.py
geowatch/cli/coco_combine_features.py
geowatch/cli/coco_crop_tracks.py
geowatch/cli/coco_reformat_channels.py
geowatch/cli/coco_remove_bad_images.py
geowatch/cli/coco_spectra.py
geowatch/cli/coco_time_combine.py
geowatch/cli/coco_update_geotiff_metadata.py
geowatch/cli/coco_visualize_videos.py
geowatch/cli/collect_env.py
geowatch/cli/concat_kwcoco_videos.py
geowatch/cli/crop_sites_to_regions.py
geowatch/cli/draw_region.py
geowatch/cli/extend_sc_sites.py
geowatch/cli/find_dvc.py
geowatch/cli/fit.py
geowatch/cli/fix_region_models.py
geowatch/cli/geojson_site_stats.py
geowatch/cli/geotiffs_to_kwcoco.py
geowatch/cli/merge_region_models.py
geowatch/cli/mlops_cli.py
geowatch/cli/predict.py
geowatch/cli/pseudolive_consolidate.py
geowatch/cli/reproject_annotations.py
geowatch/cli/run_fusion_predict.py
geowatch/cli/run_metrics_framework.py
geowatch/cli/run_tracker.py
geowatch/cli/smartflow_egress.py
geowatch/cli/smartflow_ingress.py
geowatch/cli/split_videos.py
geowatch/cli/stac_search.py
geowatch/cli/stac_to_kwcoco.py
geowatch/cli/torch_model_stats.py
geowatch/cli/validate_annotation_schemas.py
geowatch/cli/watch_coco_stats.py
geowatch/cli/experimental/__init__.py
geowatch/cli/experimental/disk_info.py
geowatch/cli/experimental/find_recent_checkpoint.py
geowatch/cli/experimental/fixup_predict_kwcoco_metadata.py
geowatch/cli/experimental/recommend_size_adjustments.py
geowatch/cli/experimental/unpack_model.py
geowatch/cli/queue_cli/__init__.py
geowatch/cli/queue_cli/prepare_cold_transfer.py
geowatch/cli/queue_cli/prepare_splits.py
geowatch-0.20.0.dist-info/licenses/LICENSE
geowatch-0.20.0.dist-info/METADATA
geowatch-0.20.0.dist-info/WHEEL
geowatch-0.20.0.dist-info/entry_points.txt
geowatch-0.20.0.dist-info/top_level.txt
geowatch-0.20.0.dist-info/RECORD
