Metadata-Version: 2.4
Name: geowatch
Version: 0.20.0
Home-page: https://gitlab.kitware.com/computer-vision/geowatch.git
Author: GeoWATCH developers
Author-email: kitware@kitware.com
License: Apache 2
Classifier: Development Status :: 4 - Beta
Classifier: Intended Audience :: Developers
Classifier: Natural Language :: English
Classifier: Programming Language :: Python :: 3
Classifier: Programming Language :: Python :: 3.10
Classifier: Programming Language :: Python :: 3.11
Requires-Python: >=3.8
License-File: LICENSE
Requires-Dist: numpy>=2.1.0; python_version < "4.0" and python_version >= "3.13"
Requires-Dist: numpy>=1.26.0; python_version < "3.13" and python_version >= "3.12"
Requires-Dist: numpy>=1.23.2; python_version < "3.12" and python_version >= "3.11"
Requires-Dist: numpy>=1.23.2; python_version < "3.11" and python_version >= "3.10"
Requires-Dist: scipy>=1.14.1; python_version < "4.0" and python_version >= "3.13"
Requires-Dist: scipy>=1.11.2; python_version < "3.13" and python_version >= "3.12"
Requires-Dist: scipy>=1.9.2; python_version < "3.12" and python_version >= "3.11"
Requires-Dist: scipy>=1.8.0; python_version < "3.11" and python_version >= "3.10"
Requires-Dist: shapely>=2.0.6; python_version < "4.0" and python_version >= "3.13"
Requires-Dist: shapely>=2.0.2; python_version < "3.13" and python_version >= "3.12"
Requires-Dist: shapely>=2.0.1; python_version < "3.12" and python_version >= "3.11"
Requires-Dist: shapely>=2.0.1; python_version < "3.11" and python_version >= "3.10"
Requires-Dist: rasterio>=1.3.11; python_version < "4.0" and python_version >= "3.13"
Requires-Dist: rasterio>=1.3.9; python_version < "3.13" and python_version >= "3.12"
Requires-Dist: rasterio>=1.3.5; python_version < "3.12" and python_version >= "3.11"
Requires-Dist: rasterio>=1.3.5; python_version < "3.11" and python_version >= "3.10"
Requires-Dist: pandas>=2.2.3; python_version < "4.0" and python_version >= "3.13"
Requires-Dist: pandas>=2.1.1; python_version < "3.13" and python_version >= "3.12"
Requires-Dist: pandas>=1.5.3; python_version < "3.12" and python_version >= "3.11"
Requires-Dist: pandas>=1.5.3; python_version < "3.11" and python_version >= "3.10"
Requires-Dist: scikit-learn>=1.5.2; python_version < "4.0" and python_version >= "3.13"
Requires-Dist: scikit-learn>=1.3.1; python_version < "3.13" and python_version >= "3.12"
Requires-Dist: scikit-learn>=1.1.3; python_version < "3.12" and python_version >= "3.11"
Requires-Dist: scikit-learn>=1.1.0; python_version < "3.11" and python_version >= "3.10"
Requires-Dist: scikit-image>=0.25.1; python_version < "4.0" and python_version >= "3.13"
Requires-Dist: scikit-image>=0.22.0; python_version < "3.13" and python_version >= "3.12"
Requires-Dist: scikit-image>=0.20.0; python_version < "3.12" and python_version >= "3.11"
Requires-Dist: scikit-image>=0.19.0; python_version < "3.11" and python_version >= "3.10"
Requires-Dist: jq>=1.8.0; python_version < "4.0" and python_version >= "3.13"
Requires-Dist: jq>=1.7.0; python_version < "3.13" and python_version >= "3.12"
Requires-Dist: jq>=1.2.2; python_version < "3.11" and python_version >= "3.10" and platform_system != "Windows"
Requires-Dist: jsonschema>=4.19.2
Requires-Dist: pyproj>=3.7.0; python_version < "4.0" and python_version >= "3.13"
Requires-Dist: pyproj>=3.6.1; python_version < "3.13" and python_version >= "3.12"
Requires-Dist: pyproj<3.5.0,>=3.4.1; python_version < "3.12" and python_version >= "3.11"
Requires-Dist: pyproj<3.5.0,>=3.3.1; python_version < "3.11" and python_version >= "3.10"
Requires-Dist: fiona>=1.10.0; python_version < "4.0" and python_version >= "3.13"
Requires-Dist: fiona>=1.9.5; python_version < "3.13" and python_version >= "3.12"
Requires-Dist: fiona<1.9.0,>=1.8.22; python_version < "3.12" and python_version >= "3.11"
Requires-Dist: fiona<1.9.0,>=1.8.22; python_version < "3.11" and python_version >= "3.10"
Requires-Dist: matplotlib>=3.9.2; python_version < "4.0" and python_version >= "3.13"
Requires-Dist: matplotlib>=3.8.2; python_version < "3.13" and python_version >= "3.12"
Requires-Dist: matplotlib>=3.8.2; python_version < "3.12" and python_version >= "3.11"
Requires-Dist: matplotlib>=3.8.2; python_version < "3.11" and python_version >= "3.10"
Requires-Dist: Pillow>=11.3.0; python_version < "4.0" and python_version >= "3.13"
Requires-Dist: Pillow>=10.2.0; python_version < "3.13"
Requires-Dist: psutil>=5.9.6; python_version < "4.0" and python_version >= "3.12"
Requires-Dist: psutil>=5.9.6; python_version < "3.12" and python_version >= "3.11"
Requires-Dist: psutil>=5.9.6; python_version < "3.11" and python_version >= "3.10"
Requires-Dist: rtree>=1.2.0; python_version >= "3.11"
Requires-Dist: rtree>=1.0.0; python_version < "3.11" and python_version >= "3.10"
Requires-Dist: sqlalchemy>=1.4.50; python_version >= "3.11"
Requires-Dist: sqlalchemy>=1.4.37; python_version < "3.11" and python_version >= "3.10"
Requires-Dist: xxhash>=3.4.1; python_version < "4.0" and python_version >= "3.12"
Requires-Dist: xxhash>=3.4.1; python_version < "3.12" and python_version >= "3.11"
Requires-Dist: xxhash>=3.0.0; python_version < "3.11" and python_version >= "3.10"
Requires-Dist: numexpr>=2.10.2; python_version < "4.0" and python_version >= "3.13"
Requires-Dist: numexpr>=2.8.7; python_version < "3.13" and python_version >= "3.12"
Requires-Dist: numexpr>=2.8.4; python_version < "3.12" and python_version >= "3.11"
Requires-Dist: numexpr>=2.8.1; python_version < "3.11" and python_version >= "3.10"
Requires-Dist: mgrs>=1.4.6; python_version < "4.0" and python_version >= "3.12"
Requires-Dist: mgrs>=1.4.6; python_version < "3.12" and python_version >= "3.11"
Requires-Dist: mgrs>=1.4.3; python_version < "3.11" and python_version >= "3.10"
Requires-Dist: kwarray>=0.6.19
Requires-Dist: xarray>=2023.10.0
Requires-Dist: einops>=0.8.0; python_version < "4.0" and python_version >= "3.13"
Requires-Dist: einops>=0.6.0; python_version < "3.13"
Requires-Dist: dask[array]>=2025.2.0; python_version < "4.0" and python_version >= "3.13"
Requires-Dist: dask[array]>=2023.5.0; python_version < "3.13"
Requires-Dist: rich>=12.5.1
Requires-Dist: textual>=0.1.18
Requires-Dist: text_unidecode>=1.3
Requires-Dist: configargparse>=1.7.1
Requires-Dist: parse>=1.19.0
Requires-Dist: affine>=2.3.0
Requires-Dist: ubelt>=1.3.6
Requires-Dist: xmltodict>=0.12.0
Requires-Dist: Pygments>=2.12.0
Requires-Dist: requests>=2.27.1
Requires-Dist: fasteners>=0.17.3
Requires-Dist: kwutil>=0.3.4
Requires-Dist: simple_dvc>=0.2.1
Requires-Dist: blake3>=1.0.1; python_version < "4.0" and python_version >= "3.13"
Requires-Dist: blake3>=1.0.1; python_version < "3.13" and python_version >= "3.12"
Requires-Dist: blake3>=0.3.1; python_version < "3.12" and python_version >= "3.11"
Requires-Dist: blake3>=0.2.1; python_version < "3.11"
Requires-Dist: more_itertools>=8.12.0
Requires-Dist: pint>=0.24.4; python_version < "4.0" and python_version >= "3.13"
Requires-Dist: pint>=0.23; python_version < "3.13"
Requires-Dist: girder_client>=3.1.15
Requires-Dist: lxml>=5.3.0; python_version < "4.0" and python_version >= "3.11"
Requires-Dist: lxml>=4.6.3; python_version < "3.11" and python_version >= "3.10"
Requires-Dist: tempenv>=0.2.0
Requires-Dist: pystac_client>=0.5.1
Requires-Dist: scriptconfig>=0.8.2
Requires-Dist: pygtrie>=2.5.0
Requires-Dist: networkx>=3.0.0; python_version < "4.0" and python_version >= "3.13"
Requires-Dist: networkx>=2.8.0; python_version < "3.12"
Requires-Dist: python_dateutil>=2.8.2
Requires-Dist: pytimeparse>=1.1.8
Requires-Dist: progiter>=2.0.0
Requires-Dist: fire>=0.4.0
Requires-Dist: lark>=1.1.7
Requires-Dist: lark_cython>=0.0.16
Requires-Dist: distinctipy>=1.2.1
Requires-Dist: kwimage>=0.11.2
Requires-Dist: kwcoco>=0.8.5
Requires-Dist: kwcoco_dataloader>=0.1.1
Requires-Dist: delayed_image>=0.4.5
Requires-Dist: albumentations==1.0.0
Requires-Dist: ndsampler>=0.8.0
Requires-Dist: tifffile>=2022.8.12; python_version < "4.0" and python_version >= "3.13"
Requires-Dist: tifffile>=2021.4.8; python_version < "3.12"
Requires-Dist: kwplot>=0.4.14
Requires-Dist: seaborn>=0.13.0
Requires-Dist: kwgis>=0.1.1
Requires-Dist: geopandas<1.0.0,>=0.14.4; python_version < "4.0" and python_version >= "3.13"
Requires-Dist: geopandas<1.0.0,>=0.10.2; python_version < "3.12" and python_version >= "3.8"
Requires-Dist: utm>=0.7.0
Requires-Dist: rgd_imagery_client>=0.2.7
Requires-Dist: rgd_client>=0.2.7
Requires-Dist: geojson>=3.1.0; python_version < "4.0" and python_version >= "3.12"
Requires-Dist: geojson>=3.0.1; python_version < "3.12" and python_version >= "3.8"
Requires-Dist: torch>=2.6.0; python_version < "4.0" and python_version >= "3.13"
Requires-Dist: torch>=2.2.0; python_version < "3.13" and python_version >= "3.12"
Requires-Dist: torch>=2.0.0; python_version < "3.12" and python_version >= "3.11"
Requires-Dist: torch>=1.12.0; python_version < "3.11"
Requires-Dist: torchvision>=0.21.0; python_version < "4.0" and python_version >= "3.13"
Requires-Dist: torchvision>=0.17.0; python_version < "3.13" and python_version >= "3.12"
Requires-Dist: torchvision>=0.15.1; python_version < "3.12" and python_version >= "3.11"
Requires-Dist: torchvision>=0.13.0; python_version < "3.11"
Requires-Dist: torchmetrics>=0.11.0
Requires-Dist: torch_liberator>=0.2.1
Requires-Dist: omegaconf>=2.3
Requires-Dist: hydra-core>=1.3.2
Requires-Dist: jsonargparse[signatures]>=4.19.0
Requires-Dist: pytorch_lightning!=2.3.*,!=2.4.0,>=2.0.8
Requires-Dist: monai>=1.3.2; python_version < "4.0" and python_version >= "3.13"
Requires-Dist: monai>=0.8.0; python_version < "3.13" and python_version >= "3.11"
Requires-Dist: monai>=0.6.0; python_version < "3.11"
Requires-Dist: torch_optimizer>=0.1.0
Requires-Dist: timm<0.9.0,>=0.6.13; python_version < "4.0" and python_version >= "3.11"
Requires-Dist: timm<0.9.0,>=0.4.12; python_version < "3.11"
Requires-Dist: kornia>=0.6.8
Requires-Dist: segmentation-models-pytorch>=0.2.0; python_version < "3.11"
Requires-Dist: ujson>=5.6.0; python_version < "4.0" and python_version >= "3.11"
Requires-Dist: ujson>=5.2.0; python_version < "3.11"
Requires-Dist: kwimage_ext>=0.2.1; platform_system == "Linux" and python_version < "3.12"
Requires-Dist: py-cpuinfo>=9.0.0
Requires-Dist: ruamel.yaml<=0.17.32,>=0.17.22
Requires-Dist: ijson>=3.2.1; python_version < "4.0" and python_version >= "3.13"
Requires-Dist: ijson>=3.2.1; python_version < "3.13" and python_version >= "3.12"
Requires-Dist: ijson>=3.2.1; python_version < "3.12" and python_version >= "3.11"
Requires-Dist: ijson>=3.2.1; python_version < "3.11" and python_version >= "3.10"
Requires-Dist: lazy_loader>=0.4
Requires-Dist: colormath>=3.0.0
Requires-Dist: imagesize>=1.4.1
Requires-Dist: pytorch_msssim==0.1.5
Requires-Dist: absl_py>=1.4.0
Requires-Dist: PyYaml>=6.0.2; python_version < "4.0" and python_version >= "3.13"
Requires-Dist: PyYaml>=6.0.1; python_version < "3.13" and python_version >= "3.12"
Requires-Dist: PyYaml>=6.0; python_version < "3.12"
Requires-Dist: tqdm>=4.64.1
Requires-Dist: cmd_queue>=0.1.20
Requires-Dist: fsspec>=2023.6.0
Requires-Dist: s3fs>=2023.6.0
Requires-Dist: portion>=2.4.1
Requires-Dist: transformers>=4.37.2
Provides-Extra: all
Requires-Dist: numpy>=2.1.0; (python_version < "4.0" and python_version >= "3.13") and extra == "all"
Requires-Dist: numpy>=1.26.0; (python_version < "3.13" and python_version >= "3.12") and extra == "all"
Requires-Dist: numpy>=1.23.2; (python_version < "3.12" and python_version >= "3.11") and extra == "all"
Requires-Dist: numpy>=1.23.2; (python_version < "3.11" and python_version >= "3.10") and extra == "all"
Requires-Dist: scipy>=1.14.1; (python_version < "4.0" and python_version >= "3.13") and extra == "all"
Requires-Dist: scipy>=1.11.2; (python_version < "3.13" and python_version >= "3.12") and extra == "all"
Requires-Dist: scipy>=1.9.2; (python_version < "3.12" and python_version >= "3.11") and extra == "all"
Requires-Dist: scipy>=1.8.0; (python_version < "3.11" and python_version >= "3.10") and extra == "all"
Requires-Dist: shapely>=2.0.6; (python_version < "4.0" and python_version >= "3.13") and extra == "all"
Requires-Dist: shapely>=2.0.2; (python_version < "3.13" and python_version >= "3.12") and extra == "all"
Requires-Dist: shapely>=2.0.1; (python_version < "3.12" and python_version >= "3.11") and extra == "all"
Requires-Dist: shapely>=2.0.1; (python_version < "3.11" and python_version >= "3.10") and extra == "all"
Requires-Dist: rasterio>=1.3.11; (python_version < "4.0" and python_version >= "3.13") and extra == "all"
Requires-Dist: rasterio>=1.3.9; (python_version < "3.13" and python_version >= "3.12") and extra == "all"
Requires-Dist: rasterio>=1.3.5; (python_version < "3.12" and python_version >= "3.11") and extra == "all"
Requires-Dist: rasterio>=1.3.5; (python_version < "3.11" and python_version >= "3.10") and extra == "all"
Requires-Dist: pandas>=2.2.3; (python_version < "4.0" and python_version >= "3.13") and extra == "all"
Requires-Dist: pandas>=2.1.1; (python_version < "3.13" and python_version >= "3.12") and extra == "all"
Requires-Dist: pandas>=1.5.3; (python_version < "3.12" and python_version >= "3.11") and extra == "all"
Requires-Dist: pandas>=1.5.3; (python_version < "3.11" and python_version >= "3.10") and extra == "all"
Requires-Dist: scikit-learn>=1.5.2; (python_version < "4.0" and python_version >= "3.13") and extra == "all"
Requires-Dist: scikit-learn>=1.3.1; (python_version < "3.13" and python_version >= "3.12") and extra == "all"
Requires-Dist: scikit-learn>=1.1.3; (python_version < "3.12" and python_version >= "3.11") and extra == "all"
Requires-Dist: scikit-learn>=1.1.0; (python_version < "3.11" and python_version >= "3.10") and extra == "all"
Requires-Dist: scikit-image>=0.25.1; (python_version < "4.0" and python_version >= "3.13") and extra == "all"
Requires-Dist: scikit-image>=0.22.0; (python_version < "3.13" and python_version >= "3.12") and extra == "all"
Requires-Dist: scikit-image>=0.20.0; (python_version < "3.12" and python_version >= "3.11") and extra == "all"
Requires-Dist: scikit-image>=0.19.0; (python_version < "3.11" and python_version >= "3.10") and extra == "all"
Requires-Dist: jq>=1.8.0; (python_version < "4.0" and python_version >= "3.13") and extra == "all"
Requires-Dist: jq>=1.7.0; (python_version < "3.13" and python_version >= "3.12") and extra == "all"
Requires-Dist: jq>=1.2.2; (python_version < "3.11" and python_version >= "3.10" and platform_system != "Windows") and extra == "all"
Requires-Dist: jsonschema>=4.19.2; extra == "all"
Requires-Dist: pyproj>=3.7.0; (python_version < "4.0" and python_version >= "3.13") and extra == "all"
Requires-Dist: pyproj>=3.6.1; (python_version < "3.13" and python_version >= "3.12") and extra == "all"
Requires-Dist: pyproj<3.5.0,>=3.4.1; (python_version < "3.12" and python_version >= "3.11") and extra == "all"
Requires-Dist: pyproj<3.5.0,>=3.3.1; (python_version < "3.11" and python_version >= "3.10") and extra == "all"
Requires-Dist: fiona>=1.10.0; (python_version < "4.0" and python_version >= "3.13") and extra == "all"
Requires-Dist: fiona>=1.9.5; (python_version < "3.13" and python_version >= "3.12") and extra == "all"
Requires-Dist: fiona<1.9.0,>=1.8.22; (python_version < "3.12" and python_version >= "3.11") and extra == "all"
Requires-Dist: fiona<1.9.0,>=1.8.22; (python_version < "3.11" and python_version >= "3.10") and extra == "all"
Requires-Dist: matplotlib>=3.9.2; (python_version < "4.0" and python_version >= "3.13") and extra == "all"
Requires-Dist: matplotlib>=3.8.2; (python_version < "3.13" and python_version >= "3.12") and extra == "all"
Requires-Dist: matplotlib>=3.8.2; (python_version < "3.12" and python_version >= "3.11") and extra == "all"
Requires-Dist: matplotlib>=3.8.2; (python_version < "3.11" and python_version >= "3.10") and extra == "all"
Requires-Dist: Pillow>=11.3.0; (python_version < "4.0" and python_version >= "3.13") and extra == "all"
Requires-Dist: Pillow>=10.2.0; python_version < "3.13" and extra == "all"
Requires-Dist: psutil>=5.9.6; (python_version < "4.0" and python_version >= "3.12") and extra == "all"
Requires-Dist: psutil>=5.9.6; (python_version < "3.12" and python_version >= "3.11") and extra == "all"
Requires-Dist: psutil>=5.9.6; (python_version < "3.11" and python_version >= "3.10") and extra == "all"
Requires-Dist: rtree>=1.2.0; python_version >= "3.11" and extra == "all"
Requires-Dist: rtree>=1.0.0; (python_version < "3.11" and python_version >= "3.10") and extra == "all"
Requires-Dist: sqlalchemy>=1.4.50; python_version >= "3.11" and extra == "all"
Requires-Dist: sqlalchemy>=1.4.37; (python_version < "3.11" and python_version >= "3.10") and extra == "all"
Requires-Dist: xxhash>=3.4.1; (python_version < "4.0" and python_version >= "3.12") and extra == "all"
Requires-Dist: xxhash>=3.4.1; (python_version < "3.12" and python_version >= "3.11") and extra == "all"
Requires-Dist: xxhash>=3.0.0; (python_version < "3.11" and python_version >= "3.10") and extra == "all"
Requires-Dist: numexpr>=2.10.2; (python_version < "4.0" and python_version >= "3.13") and extra == "all"
Requires-Dist: numexpr>=2.8.7; (python_version < "3.13" and python_version >= "3.12") and extra == "all"
Requires-Dist: numexpr>=2.8.4; (python_version < "3.12" and python_version >= "3.11") and extra == "all"
Requires-Dist: numexpr>=2.8.1; (python_version < "3.11" and python_version >= "3.10") and extra == "all"
Requires-Dist: mgrs>=1.4.6; (python_version < "4.0" and python_version >= "3.12") and extra == "all"
Requires-Dist: mgrs>=1.4.6; (python_version < "3.12" and python_version >= "3.11") and extra == "all"
Requires-Dist: mgrs>=1.4.3; (python_version < "3.11" and python_version >= "3.10") and extra == "all"
Requires-Dist: kwarray>=0.6.19; extra == "all"
Requires-Dist: xarray>=2023.10.0; extra == "all"
Requires-Dist: einops>=0.8.0; (python_version < "4.0" and python_version >= "3.13") and extra == "all"
Requires-Dist: einops>=0.6.0; python_version < "3.13" and extra == "all"
Requires-Dist: dask[array]>=2025.2.0; (python_version < "4.0" and python_version >= "3.13") and extra == "all"
Requires-Dist: dask[array]>=2023.5.0; python_version < "3.13" and extra == "all"
Requires-Dist: rich>=12.5.1; extra == "all"
Requires-Dist: textual>=0.1.18; extra == "all"
Requires-Dist: text_unidecode>=1.3; extra == "all"
Requires-Dist: configargparse>=1.7.1; extra == "all"
Requires-Dist: parse>=1.19.0; extra == "all"
Requires-Dist: affine>=2.3.0; extra == "all"
Requires-Dist: ubelt>=1.3.6; extra == "all"
Requires-Dist: xmltodict>=0.12.0; extra == "all"
Requires-Dist: Pygments>=2.12.0; extra == "all"
Requires-Dist: requests>=2.27.1; extra == "all"
Requires-Dist: fasteners>=0.17.3; extra == "all"
Requires-Dist: kwutil>=0.3.4; extra == "all"
Requires-Dist: simple_dvc>=0.2.1; extra == "all"
Requires-Dist: blake3>=1.0.1; (python_version < "4.0" and python_version >= "3.13") and extra == "all"
Requires-Dist: blake3>=1.0.1; (python_version < "3.13" and python_version >= "3.12") and extra == "all"
Requires-Dist: blake3>=0.3.1; (python_version < "3.12" and python_version >= "3.11") and extra == "all"
Requires-Dist: blake3>=0.2.1; python_version < "3.11" and extra == "all"
Requires-Dist: more_itertools>=8.12.0; extra == "all"
Requires-Dist: pint>=0.24.4; (python_version < "4.0" and python_version >= "3.13") and extra == "all"
Requires-Dist: pint>=0.23; python_version < "3.13" and extra == "all"
Requires-Dist: girder_client>=3.1.15; extra == "all"
Requires-Dist: lxml>=5.3.0; (python_version < "4.0" and python_version >= "3.11") and extra == "all"
Requires-Dist: lxml>=4.6.3; (python_version < "3.11" and python_version >= "3.10") and extra == "all"
Requires-Dist: tempenv>=0.2.0; extra == "all"
Requires-Dist: pystac_client>=0.5.1; extra == "all"
Requires-Dist: scriptconfig>=0.8.2; extra == "all"
Requires-Dist: pygtrie>=2.5.0; extra == "all"
Requires-Dist: networkx>=3.0.0; (python_version < "4.0" and python_version >= "3.13") and extra == "all"
Requires-Dist: networkx>=2.8.0; python_version < "3.12" and extra == "all"
Requires-Dist: python_dateutil>=2.8.2; extra == "all"
Requires-Dist: pytimeparse>=1.1.8; extra == "all"
Requires-Dist: progiter>=2.0.0; extra == "all"
Requires-Dist: fire>=0.4.0; extra == "all"
Requires-Dist: lark>=1.1.7; extra == "all"
Requires-Dist: lark_cython>=0.0.16; extra == "all"
Requires-Dist: distinctipy>=1.2.1; extra == "all"
Requires-Dist: kwimage>=0.11.2; extra == "all"
Requires-Dist: kwcoco>=0.8.5; extra == "all"
Requires-Dist: kwcoco_dataloader>=0.1.1; extra == "all"
Requires-Dist: delayed_image>=0.4.5; extra == "all"
Requires-Dist: albumentations==1.0.0; extra == "all"
Requires-Dist: ndsampler>=0.8.0; extra == "all"
Requires-Dist: tifffile>=2022.8.12; (python_version < "4.0" and python_version >= "3.13") and extra == "all"
Requires-Dist: tifffile>=2021.4.8; python_version < "3.12" and extra == "all"
Requires-Dist: kwplot>=0.4.14; extra == "all"
Requires-Dist: seaborn>=0.13.0; extra == "all"
Requires-Dist: kwgis>=0.1.1; extra == "all"
Requires-Dist: geopandas<1.0.0,>=0.14.4; (python_version < "4.0" and python_version >= "3.13") and extra == "all"
Requires-Dist: geopandas<1.0.0,>=0.10.2; (python_version < "3.12" and python_version >= "3.8") and extra == "all"
Requires-Dist: utm>=0.7.0; extra == "all"
Requires-Dist: rgd_imagery_client>=0.2.7; extra == "all"
Requires-Dist: rgd_client>=0.2.7; extra == "all"
Requires-Dist: geojson>=3.1.0; (python_version < "4.0" and python_version >= "3.12") and extra == "all"
Requires-Dist: geojson>=3.0.1; (python_version < "3.12" and python_version >= "3.8") and extra == "all"
Requires-Dist: torch>=2.6.0; (python_version < "4.0" and python_version >= "3.13") and extra == "all"
Requires-Dist: torch>=2.2.0; (python_version < "3.13" and python_version >= "3.12") and extra == "all"
Requires-Dist: torch>=2.0.0; (python_version < "3.12" and python_version >= "3.11") and extra == "all"
Requires-Dist: torch>=1.12.0; python_version < "3.11" and extra == "all"
Requires-Dist: torchvision>=0.21.0; (python_version < "4.0" and python_version >= "3.13") and extra == "all"
Requires-Dist: torchvision>=0.17.0; (python_version < "3.13" and python_version >= "3.12") and extra == "all"
Requires-Dist: torchvision>=0.15.1; (python_version < "3.12" and python_version >= "3.11") and extra == "all"
Requires-Dist: torchvision>=0.13.0; python_version < "3.11" and extra == "all"
Requires-Dist: torchmetrics>=0.11.0; extra == "all"
Requires-Dist: torch_liberator>=0.2.1; extra == "all"
Requires-Dist: omegaconf>=2.3; extra == "all"
Requires-Dist: hydra-core>=1.3.2; extra == "all"
Requires-Dist: jsonargparse[signatures]>=4.19.0; extra == "all"
Requires-Dist: pytorch_lightning!=2.3.*,!=2.4.0,>=2.0.8; extra == "all"
Requires-Dist: monai>=1.3.2; (python_version < "4.0" and python_version >= "3.13") and extra == "all"
Requires-Dist: monai>=0.8.0; (python_version < "3.13" and python_version >= "3.11") and extra == "all"
Requires-Dist: monai>=0.6.0; python_version < "3.11" and extra == "all"
Requires-Dist: torch_optimizer>=0.1.0; extra == "all"
Requires-Dist: timm<0.9.0,>=0.6.13; (python_version < "4.0" and python_version >= "3.11") and extra == "all"
Requires-Dist: timm<0.9.0,>=0.4.12; python_version < "3.11" and extra == "all"
Requires-Dist: kornia>=0.6.8; extra == "all"
Requires-Dist: segmentation-models-pytorch>=0.2.0; python_version < "3.11" and extra == "all"
Requires-Dist: ujson>=5.6.0; (python_version < "4.0" and python_version >= "3.11") and extra == "all"
Requires-Dist: ujson>=5.2.0; python_version < "3.11" and extra == "all"
Requires-Dist: kwimage_ext>=0.2.1; (platform_system == "Linux" and python_version < "3.12") and extra == "all"
Requires-Dist: py-cpuinfo>=9.0.0; extra == "all"
Requires-Dist: ruamel.yaml<=0.17.32,>=0.17.22; extra == "all"
Requires-Dist: ijson>=3.2.1; (python_version < "4.0" and python_version >= "3.13") and extra == "all"
Requires-Dist: ijson>=3.2.1; (python_version < "3.13" and python_version >= "3.12") and extra == "all"
Requires-Dist: ijson>=3.2.1; (python_version < "3.12" and python_version >= "3.11") and extra == "all"
Requires-Dist: ijson>=3.2.1; (python_version < "3.11" and python_version >= "3.10") and extra == "all"
Requires-Dist: lazy_loader>=0.4; extra == "all"
Requires-Dist: colormath>=3.0.0; extra == "all"
Requires-Dist: imagesize>=1.4.1; extra == "all"
Requires-Dist: pytorch_msssim==0.1.5; extra == "all"
Requires-Dist: absl_py>=1.4.0; extra == "all"
Requires-Dist: PyYaml>=6.0.2; (python_version < "4.0" and python_version >= "3.13") and extra == "all"
Requires-Dist: PyYaml>=6.0.1; (python_version < "3.13" and python_version >= "3.12") and extra == "all"
Requires-Dist: PyYaml>=6.0; python_version < "3.12" and extra == "all"
Requires-Dist: tqdm>=4.64.1; extra == "all"
Requires-Dist: cmd_queue>=0.1.20; extra == "all"
Requires-Dist: fsspec>=2023.6.0; extra == "all"
Requires-Dist: s3fs>=2023.6.0; extra == "all"
Requires-Dist: portion>=2.4.1; extra == "all"
Requires-Dist: transformers>=4.37.2; extra == "all"
Requires-Dist: pytest>=8.0.2; extra == "all"
Requires-Dist: xdoctest>=1.1.5; extra == "all"
Requires-Dist: pytest-cov>=3.0.0; extra == "all"
Requires-Dist: coverage>=7.4.3; extra == "all"
Requires-Dist: geodatasets>=2023.12.0; extra == "all"
Requires-Dist: PyQt5>=5.15; extra == "all"
Requires-Dist: ipython>=8.13.1; extra == "all"
Requires-Dist: flake8>=5.0.0; extra == "all"
Requires-Dist: autopep8>=2.0.0; extra == "all"
Requires-Dist: mkinit>=0.3.3; extra == "all"
Requires-Dist: timerit>=0.3.0; extra == "all"
Requires-Dist: codecarbon>=2.2.4; extra == "all"
Requires-Dist: humanize>=4.8.0; extra == "all"
Requires-Dist: rich_argparse>=1.1.0; python_version >= "3.7" and extra == "all"
Requires-Dist: argcomplete>=3.0.5; extra == "all"
Requires-Dist: levenshtein>=0.26.1; (python_version < "4.0" and python_version >= "3.13") and extra == "all"
Requires-Dist: levenshtein>=0.22.0; (python_version < "3.13" and python_version >= "3.12") and extra == "all"
Requires-Dist: levenshtein>=0.20.8; (python_version < "3.12" and python_version >= "3.11") and extra == "all"
Requires-Dist: Levenshtein>=0.16.0; (python_version < "3.11" and python_version >= "3.10") and extra == "all"
Requires-Dist: simplekml>=1.3.3; extra == "all"
Provides-Extra: aws
Requires-Dist: botocore>=1.31.17; extra == "aws"
Requires-Dist: s3transfer>=0.6.2; extra == "aws"
Requires-Dist: s3fs>=2023.6.0; extra == "aws"
Provides-Extra: aws-strict
Requires-Dist: botocore==1.31.17; extra == "aws-strict"
Requires-Dist: s3transfer==0.6.2; extra == "aws-strict"
Requires-Dist: s3fs==2023.6.0; extra == "aws-strict"
Provides-Extra: cold
Requires-Dist: astropy>=5.2.2; (python_version < "4.0" and python_version >= "3.11") and extra == "cold"
Requires-Dist: astropy>=5.1; (python_version < "3.11" and python_version >= "3.10") and extra == "cold"
Requires-Dist: pycold>=0.1.2; extra == "cold"
Provides-Extra: cold-strict
Requires-Dist: astropy==5.2.2; (python_version < "4.0" and python_version >= "3.11") and extra == "cold-strict"
Requires-Dist: astropy==5.1; (python_version < "3.11" and python_version >= "3.10") and extra == "cold-strict"
Requires-Dist: pycold==0.1.2; extra == "cold-strict"
Provides-Extra: development
Requires-Dist: tensorboard>=2.14.0; extra == "development"
Requires-Dist: performer_pytorch>=1.0.11; extra == "development"
Requires-Dist: reformer_pytorch>=1.4.3; extra == "development"
Requires-Dist: perceiver-pytorch>=0.8.3; extra == "development"
Requires-Dist: torch_optimizer>=0.1.0; python_version >= "3.6" and extra == "development"
Requires-Dist: openpyxl>=3.0.9; extra == "development"
Requires-Dist: textual>=0.1.18; extra == "development"
Requires-Dist: dataframe_image>=0.1.13; extra == "development"
Requires-Dist: wrapt>=1.14.1; extra == "development"
Provides-Extra: development-strict
Requires-Dist: tensorboard==2.14.0; extra == "development-strict"
Requires-Dist: performer_pytorch==1.0.11; extra == "development-strict"
Requires-Dist: reformer_pytorch==1.4.3; extra == "development-strict"
Requires-Dist: perceiver-pytorch==0.8.3; extra == "development-strict"
Requires-Dist: torch_optimizer==0.1.0; python_version >= "3.6" and extra == "development-strict"
Requires-Dist: openpyxl==3.0.9; extra == "development-strict"
Requires-Dist: textual==0.1.18; extra == "development-strict"
Requires-Dist: dataframe_image==0.1.13; extra == "development-strict"
Requires-Dist: wrapt==1.14.1; extra == "development-strict"
Provides-Extra: dvc
Requires-Dist: dvc[s3,ssh]>=3.7.0; extra == "dvc"
Requires-Dist: simple_dvc>=0.2.1; extra == "dvc"
Provides-Extra: dvc-strict
Requires-Dist: dvc[s3,ssh]==3.7.0; extra == "dvc-strict"
Requires-Dist: simple_dvc==0.2.1; extra == "dvc-strict"
Provides-Extra: gdal
Requires-Dist: GDAL>=3.10.0; (python_version < "4.0" and python_version >= "3.13") and extra == "gdal"
Requires-Dist: GDAL>=3.7.2; (python_version < "3.13" and python_version >= "3.12") and extra == "gdal"
Requires-Dist: GDAL>=3.5.2; (python_version < "3.12" and python_version >= "3.11") and extra == "gdal"
Requires-Dist: GDAL<=3.11.0,>=3.4.1; (python_version < "3.11" and python_version >= "3.10") and extra == "gdal"
Provides-Extra: gdal-strict
Requires-Dist: GDAL==3.10.0; (python_version < "4.0" and python_version >= "3.13") and extra == "gdal-strict"
Requires-Dist: GDAL==3.7.2; (python_version < "3.13" and python_version >= "3.12") and extra == "gdal-strict"
Requires-Dist: GDAL==3.5.2; (python_version < "3.12" and python_version >= "3.11") and extra == "gdal-strict"
Requires-Dist: GDAL<=3.11.0,==3.4.1; (python_version < "3.11" and python_version >= "3.10") and extra == "gdal-strict"
Provides-Extra: linting
Requires-Dist: flake8>=5.0.0; extra == "linting"
Requires-Dist: ubelt>=1.3.6; extra == "linting"
Requires-Dist: fire>=0.4.0; extra == "linting"
Requires-Dist: rich>=12.5.1; extra == "linting"
Requires-Dist: xdev>=1.5.3; extra == "linting"
Provides-Extra: linting-strict
Requires-Dist: flake8==5.0.0; extra == "linting-strict"
Requires-Dist: ubelt==1.3.6; extra == "linting-strict"
Requires-Dist: fire==0.4.0; extra == "linting-strict"
Requires-Dist: rich==12.5.1; extra == "linting-strict"
Requires-Dist: xdev==1.5.3; extra == "linting-strict"
Provides-Extra: materials
Requires-Dist: segmentation_models_pytorch>=0.3.0; extra == "materials"
Requires-Dist: pycm>=3.6; extra == "materials"
Provides-Extra: materials-strict
Requires-Dist: segmentation_models_pytorch==0.3.0; extra == "materials-strict"
Requires-Dist: pycm==3.6; extra == "materials-strict"
Provides-Extra: mmcv
Requires-Dist: mmcv>=2.0.0; extra == "mmcv"
Provides-Extra: mmcv-strict
Requires-Dist: mmcv==2.0.0; extra == "mmcv-strict"
Provides-Extra: optional
Requires-Dist: PyQt5>=5.15; extra == "optional"
Requires-Dist: ipython>=8.13.1; extra == "optional"
Requires-Dist: flake8>=5.0.0; extra == "optional"
Requires-Dist: autopep8>=2.0.0; extra == "optional"
Requires-Dist: mkinit>=0.3.3; extra == "optional"
Requires-Dist: timerit>=0.3.0; extra == "optional"
Requires-Dist: codecarbon>=2.2.4; extra == "optional"
Requires-Dist: humanize>=4.8.0; extra == "optional"
Requires-Dist: rich_argparse>=1.1.0; python_version >= "3.7" and extra == "optional"
Requires-Dist: argcomplete>=3.0.5; extra == "optional"
Requires-Dist: levenshtein>=0.26.1; (python_version < "4.0" and python_version >= "3.13") and extra == "optional"
Requires-Dist: levenshtein>=0.22.0; (python_version < "3.13" and python_version >= "3.12") and extra == "optional"
Requires-Dist: levenshtein>=0.20.8; (python_version < "3.12" and python_version >= "3.11") and extra == "optional"
Requires-Dist: Levenshtein>=0.16.0; (python_version < "3.11" and python_version >= "3.10") and extra == "optional"
Requires-Dist: simplekml>=1.3.3; extra == "optional"
Provides-Extra: optional-strict
Requires-Dist: PyQt5==5.15; extra == "optional-strict"
Requires-Dist: ipython==8.13.1; extra == "optional-strict"
Requires-Dist: flake8==5.0.0; extra == "optional-strict"
Requires-Dist: autopep8==2.0.0; extra == "optional-strict"
Requires-Dist: mkinit==0.3.3; extra == "optional-strict"
Requires-Dist: timerit==0.3.0; extra == "optional-strict"
Requires-Dist: codecarbon==2.2.4; extra == "optional-strict"
Requires-Dist: humanize==4.8.0; extra == "optional-strict"
Requires-Dist: rich_argparse==1.1.0; python_version >= "3.7" and extra == "optional-strict"
Requires-Dist: argcomplete==3.0.5; extra == "optional-strict"
Requires-Dist: levenshtein==0.26.1; (python_version < "4.0" and python_version >= "3.13") and extra == "optional-strict"
Requires-Dist: levenshtein==0.22.0; (python_version < "3.13" and python_version >= "3.12") and extra == "optional-strict"
Requires-Dist: levenshtein==0.20.8; (python_version < "3.12" and python_version >= "3.11") and extra == "optional-strict"
Requires-Dist: Levenshtein==0.16.0; (python_version < "3.11" and python_version >= "3.10") and extra == "optional-strict"
Requires-Dist: simplekml==1.3.3; extra == "optional-strict"
Provides-Extra: python-build-tools
Requires-Dist: pip>=23.1.2; extra == "python-build-tools"
Requires-Dist: setuptools>=67.7.2; extra == "python-build-tools"
Requires-Dist: wheel>=0.40.0; extra == "python-build-tools"
Requires-Dist: build>=0.10.0; extra == "python-build-tools"
Provides-Extra: python-build-tools-strict
Requires-Dist: pip==23.1.2; extra == "python-build-tools-strict"
Requires-Dist: setuptools==67.7.2; extra == "python-build-tools-strict"
Requires-Dist: wheel==0.40.0; extra == "python-build-tools-strict"
Requires-Dist: build==0.10.0; extra == "python-build-tools-strict"
Provides-Extra: runtime
Requires-Dist: numpy>=2.1.0; (python_version < "4.0" and python_version >= "3.13") and extra == "runtime"
Requires-Dist: numpy>=1.26.0; (python_version < "3.13" and python_version >= "3.12") and extra == "runtime"
Requires-Dist: numpy>=1.23.2; (python_version < "3.12" and python_version >= "3.11") and extra == "runtime"
Requires-Dist: numpy>=1.23.2; (python_version < "3.11" and python_version >= "3.10") and extra == "runtime"
Requires-Dist: scipy>=1.14.1; (python_version < "4.0" and python_version >= "3.13") and extra == "runtime"
Requires-Dist: scipy>=1.11.2; (python_version < "3.13" and python_version >= "3.12") and extra == "runtime"
Requires-Dist: scipy>=1.9.2; (python_version < "3.12" and python_version >= "3.11") and extra == "runtime"
Requires-Dist: scipy>=1.8.0; (python_version < "3.11" and python_version >= "3.10") and extra == "runtime"
Requires-Dist: shapely>=2.0.6; (python_version < "4.0" and python_version >= "3.13") and extra == "runtime"
Requires-Dist: shapely>=2.0.2; (python_version < "3.13" and python_version >= "3.12") and extra == "runtime"
Requires-Dist: shapely>=2.0.1; (python_version < "3.12" and python_version >= "3.11") and extra == "runtime"
Requires-Dist: shapely>=2.0.1; (python_version < "3.11" and python_version >= "3.10") and extra == "runtime"
Requires-Dist: rasterio>=1.3.11; (python_version < "4.0" and python_version >= "3.13") and extra == "runtime"
Requires-Dist: rasterio>=1.3.9; (python_version < "3.13" and python_version >= "3.12") and extra == "runtime"
Requires-Dist: rasterio>=1.3.5; (python_version < "3.12" and python_version >= "3.11") and extra == "runtime"
Requires-Dist: rasterio>=1.3.5; (python_version < "3.11" and python_version >= "3.10") and extra == "runtime"
Requires-Dist: pandas>=2.2.3; (python_version < "4.0" and python_version >= "3.13") and extra == "runtime"
Requires-Dist: pandas>=2.1.1; (python_version < "3.13" and python_version >= "3.12") and extra == "runtime"
Requires-Dist: pandas>=1.5.3; (python_version < "3.12" and python_version >= "3.11") and extra == "runtime"
Requires-Dist: pandas>=1.5.3; (python_version < "3.11" and python_version >= "3.10") and extra == "runtime"
Requires-Dist: scikit-learn>=1.5.2; (python_version < "4.0" and python_version >= "3.13") and extra == "runtime"
Requires-Dist: scikit-learn>=1.3.1; (python_version < "3.13" and python_version >= "3.12") and extra == "runtime"
Requires-Dist: scikit-learn>=1.1.3; (python_version < "3.12" and python_version >= "3.11") and extra == "runtime"
Requires-Dist: scikit-learn>=1.1.0; (python_version < "3.11" and python_version >= "3.10") and extra == "runtime"
Requires-Dist: scikit-image>=0.25.1; (python_version < "4.0" and python_version >= "3.13") and extra == "runtime"
Requires-Dist: scikit-image>=0.22.0; (python_version < "3.13" and python_version >= "3.12") and extra == "runtime"
Requires-Dist: scikit-image>=0.20.0; (python_version < "3.12" and python_version >= "3.11") and extra == "runtime"
Requires-Dist: scikit-image>=0.19.0; (python_version < "3.11" and python_version >= "3.10") and extra == "runtime"
Requires-Dist: jq>=1.8.0; (python_version < "4.0" and python_version >= "3.13") and extra == "runtime"
Requires-Dist: jq>=1.7.0; (python_version < "3.13" and python_version >= "3.12") and extra == "runtime"
Requires-Dist: jq>=1.2.2; (python_version < "3.11" and python_version >= "3.10" and platform_system != "Windows") and extra == "runtime"
Requires-Dist: jsonschema>=4.19.2; extra == "runtime"
Requires-Dist: pyproj>=3.7.0; (python_version < "4.0" and python_version >= "3.13") and extra == "runtime"
Requires-Dist: pyproj>=3.6.1; (python_version < "3.13" and python_version >= "3.12") and extra == "runtime"
Requires-Dist: pyproj<3.5.0,>=3.4.1; (python_version < "3.12" and python_version >= "3.11") and extra == "runtime"
Requires-Dist: pyproj<3.5.0,>=3.3.1; (python_version < "3.11" and python_version >= "3.10") and extra == "runtime"
Requires-Dist: fiona>=1.10.0; (python_version < "4.0" and python_version >= "3.13") and extra == "runtime"
Requires-Dist: fiona>=1.9.5; (python_version < "3.13" and python_version >= "3.12") and extra == "runtime"
Requires-Dist: fiona<1.9.0,>=1.8.22; (python_version < "3.12" and python_version >= "3.11") and extra == "runtime"
Requires-Dist: fiona<1.9.0,>=1.8.22; (python_version < "3.11" and python_version >= "3.10") and extra == "runtime"
Requires-Dist: matplotlib>=3.9.2; (python_version < "4.0" and python_version >= "3.13") and extra == "runtime"
Requires-Dist: matplotlib>=3.8.2; (python_version < "3.13" and python_version >= "3.12") and extra == "runtime"
Requires-Dist: matplotlib>=3.8.2; (python_version < "3.12" and python_version >= "3.11") and extra == "runtime"
Requires-Dist: matplotlib>=3.8.2; (python_version < "3.11" and python_version >= "3.10") and extra == "runtime"
Requires-Dist: Pillow>=11.3.0; (python_version < "4.0" and python_version >= "3.13") and extra == "runtime"
Requires-Dist: Pillow>=10.2.0; python_version < "3.13" and extra == "runtime"
Requires-Dist: psutil>=5.9.6; (python_version < "4.0" and python_version >= "3.12") and extra == "runtime"
Requires-Dist: psutil>=5.9.6; (python_version < "3.12" and python_version >= "3.11") and extra == "runtime"
Requires-Dist: psutil>=5.9.6; (python_version < "3.11" and python_version >= "3.10") and extra == "runtime"
Requires-Dist: rtree>=1.2.0; python_version >= "3.11" and extra == "runtime"
Requires-Dist: rtree>=1.0.0; (python_version < "3.11" and python_version >= "3.10") and extra == "runtime"
Requires-Dist: sqlalchemy>=1.4.50; python_version >= "3.11" and extra == "runtime"
Requires-Dist: sqlalchemy>=1.4.37; (python_version < "3.11" and python_version >= "3.10") and extra == "runtime"
Requires-Dist: xxhash>=3.4.1; (python_version < "4.0" and python_version >= "3.12") and extra == "runtime"
Requires-Dist: xxhash>=3.4.1; (python_version < "3.12" and python_version >= "3.11") and extra == "runtime"
Requires-Dist: xxhash>=3.0.0; (python_version < "3.11" and python_version >= "3.10") and extra == "runtime"
Requires-Dist: numexpr>=2.10.2; (python_version < "4.0" and python_version >= "3.13") and extra == "runtime"
Requires-Dist: numexpr>=2.8.7; (python_version < "3.13" and python_version >= "3.12") and extra == "runtime"
Requires-Dist: numexpr>=2.8.4; (python_version < "3.12" and python_version >= "3.11") and extra == "runtime"
Requires-Dist: numexpr>=2.8.1; (python_version < "3.11" and python_version >= "3.10") and extra == "runtime"
Requires-Dist: mgrs>=1.4.6; (python_version < "4.0" and python_version >= "3.12") and extra == "runtime"
Requires-Dist: mgrs>=1.4.6; (python_version < "3.12" and python_version >= "3.11") and extra == "runtime"
Requires-Dist: mgrs>=1.4.3; (python_version < "3.11" and python_version >= "3.10") and extra == "runtime"
Requires-Dist: kwarray>=0.6.19; extra == "runtime"
Requires-Dist: xarray>=2023.10.0; extra == "runtime"
Requires-Dist: einops>=0.8.0; (python_version < "4.0" and python_version >= "3.13") and extra == "runtime"
Requires-Dist: einops>=0.6.0; python_version < "3.13" and extra == "runtime"
Requires-Dist: dask[array]>=2025.2.0; (python_version < "4.0" and python_version >= "3.13") and extra == "runtime"
Requires-Dist: dask[array]>=2023.5.0; python_version < "3.13" and extra == "runtime"
Requires-Dist: rich>=12.5.1; extra == "runtime"
Requires-Dist: textual>=0.1.18; extra == "runtime"
Requires-Dist: text_unidecode>=1.3; extra == "runtime"
Requires-Dist: configargparse>=1.7.1; extra == "runtime"
Requires-Dist: parse>=1.19.0; extra == "runtime"
Requires-Dist: affine>=2.3.0; extra == "runtime"
Requires-Dist: ubelt>=1.3.6; extra == "runtime"
Requires-Dist: xmltodict>=0.12.0; extra == "runtime"
Requires-Dist: Pygments>=2.12.0; extra == "runtime"
Requires-Dist: requests>=2.27.1; extra == "runtime"
Requires-Dist: fasteners>=0.17.3; extra == "runtime"
Requires-Dist: kwutil>=0.3.4; extra == "runtime"
Requires-Dist: simple_dvc>=0.2.1; extra == "runtime"
Requires-Dist: blake3>=1.0.1; (python_version < "4.0" and python_version >= "3.13") and extra == "runtime"
Requires-Dist: blake3>=1.0.1; (python_version < "3.13" and python_version >= "3.12") and extra == "runtime"
Requires-Dist: blake3>=0.3.1; (python_version < "3.12" and python_version >= "3.11") and extra == "runtime"
Requires-Dist: blake3>=0.2.1; python_version < "3.11" and extra == "runtime"
Requires-Dist: more_itertools>=8.12.0; extra == "runtime"
Requires-Dist: pint>=0.24.4; (python_version < "4.0" and python_version >= "3.13") and extra == "runtime"
Requires-Dist: pint>=0.23; python_version < "3.13" and extra == "runtime"
Requires-Dist: girder_client>=3.1.15; extra == "runtime"
Requires-Dist: lxml>=5.3.0; (python_version < "4.0" and python_version >= "3.11") and extra == "runtime"
Requires-Dist: lxml>=4.6.3; (python_version < "3.11" and python_version >= "3.10") and extra == "runtime"
Requires-Dist: tempenv>=0.2.0; extra == "runtime"
Requires-Dist: pystac_client>=0.5.1; extra == "runtime"
Requires-Dist: scriptconfig>=0.8.2; extra == "runtime"
Requires-Dist: pygtrie>=2.5.0; extra == "runtime"
Requires-Dist: networkx>=3.0.0; (python_version < "4.0" and python_version >= "3.13") and extra == "runtime"
Requires-Dist: networkx>=2.8.0; python_version < "3.12" and extra == "runtime"
Requires-Dist: python_dateutil>=2.8.2; extra == "runtime"
Requires-Dist: pytimeparse>=1.1.8; extra == "runtime"
Requires-Dist: progiter>=2.0.0; extra == "runtime"
Requires-Dist: fire>=0.4.0; extra == "runtime"
Requires-Dist: lark>=1.1.7; extra == "runtime"
Requires-Dist: lark_cython>=0.0.16; extra == "runtime"
Requires-Dist: distinctipy>=1.2.1; extra == "runtime"
Requires-Dist: kwimage>=0.11.2; extra == "runtime"
Requires-Dist: kwcoco>=0.8.5; extra == "runtime"
Requires-Dist: kwcoco_dataloader>=0.1.1; extra == "runtime"
Requires-Dist: delayed_image>=0.4.5; extra == "runtime"
Requires-Dist: albumentations==1.0.0; extra == "runtime"
Requires-Dist: ndsampler>=0.8.0; extra == "runtime"
Requires-Dist: tifffile>=2022.8.12; (python_version < "4.0" and python_version >= "3.13") and extra == "runtime"
Requires-Dist: tifffile>=2021.4.8; python_version < "3.12" and extra == "runtime"
Requires-Dist: kwplot>=0.4.14; extra == "runtime"
Requires-Dist: seaborn>=0.13.0; extra == "runtime"
Requires-Dist: kwgis>=0.1.1; extra == "runtime"
Requires-Dist: geopandas<1.0.0,>=0.14.4; (python_version < "4.0" and python_version >= "3.13") and extra == "runtime"
Requires-Dist: geopandas<1.0.0,>=0.10.2; (python_version < "3.12" and python_version >= "3.8") and extra == "runtime"
Requires-Dist: utm>=0.7.0; extra == "runtime"
Requires-Dist: rgd_imagery_client>=0.2.7; extra == "runtime"
Requires-Dist: rgd_client>=0.2.7; extra == "runtime"
Requires-Dist: geojson>=3.1.0; (python_version < "4.0" and python_version >= "3.12") and extra == "runtime"
Requires-Dist: geojson>=3.0.1; (python_version < "3.12" and python_version >= "3.8") and extra == "runtime"
Requires-Dist: torch>=2.6.0; (python_version < "4.0" and python_version >= "3.13") and extra == "runtime"
Requires-Dist: torch>=2.2.0; (python_version < "3.13" and python_version >= "3.12") and extra == "runtime"
Requires-Dist: torch>=2.0.0; (python_version < "3.12" and python_version >= "3.11") and extra == "runtime"
Requires-Dist: torch>=1.12.0; python_version < "3.11" and extra == "runtime"
Requires-Dist: torchvision>=0.21.0; (python_version < "4.0" and python_version >= "3.13") and extra == "runtime"
Requires-Dist: torchvision>=0.17.0; (python_version < "3.13" and python_version >= "3.12") and extra == "runtime"
Requires-Dist: torchvision>=0.15.1; (python_version < "3.12" and python_version >= "3.11") and extra == "runtime"
Requires-Dist: torchvision>=0.13.0; python_version < "3.11" and extra == "runtime"
Requires-Dist: torchmetrics>=0.11.0; extra == "runtime"
Requires-Dist: torch_liberator>=0.2.1; extra == "runtime"
Requires-Dist: omegaconf>=2.3; extra == "runtime"
Requires-Dist: hydra-core>=1.3.2; extra == "runtime"
Requires-Dist: jsonargparse[signatures]>=4.19.0; extra == "runtime"
Requires-Dist: pytorch_lightning!=2.3.*,!=2.4.0,>=2.0.8; extra == "runtime"
Requires-Dist: monai>=1.3.2; (python_version < "4.0" and python_version >= "3.13") and extra == "runtime"
Requires-Dist: monai>=0.8.0; (python_version < "3.13" and python_version >= "3.11") and extra == "runtime"
Requires-Dist: monai>=0.6.0; python_version < "3.11" and extra == "runtime"
Requires-Dist: torch_optimizer>=0.1.0; extra == "runtime"
Requires-Dist: timm<0.9.0,>=0.6.13; (python_version < "4.0" and python_version >= "3.11") and extra == "runtime"
Requires-Dist: timm<0.9.0,>=0.4.12; python_version < "3.11" and extra == "runtime"
Requires-Dist: kornia>=0.6.8; extra == "runtime"
Requires-Dist: segmentation-models-pytorch>=0.2.0; python_version < "3.11" and extra == "runtime"
Requires-Dist: ujson>=5.6.0; (python_version < "4.0" and python_version >= "3.11") and extra == "runtime"
Requires-Dist: ujson>=5.2.0; python_version < "3.11" and extra == "runtime"
Requires-Dist: kwimage_ext>=0.2.1; (platform_system == "Linux" and python_version < "3.12") and extra == "runtime"
Requires-Dist: py-cpuinfo>=9.0.0; extra == "runtime"
Requires-Dist: ruamel.yaml<=0.17.32,>=0.17.22; extra == "runtime"
Requires-Dist: ijson>=3.2.1; (python_version < "4.0" and python_version >= "3.13") and extra == "runtime"
Requires-Dist: ijson>=3.2.1; (python_version < "3.13" and python_version >= "3.12") and extra == "runtime"
Requires-Dist: ijson>=3.2.1; (python_version < "3.12" and python_version >= "3.11") and extra == "runtime"
Requires-Dist: ijson>=3.2.1; (python_version < "3.11" and python_version >= "3.10") and extra == "runtime"
Requires-Dist: lazy_loader>=0.4; extra == "runtime"
Requires-Dist: colormath>=3.0.0; extra == "runtime"
Requires-Dist: imagesize>=1.4.1; extra == "runtime"
Requires-Dist: pytorch_msssim==0.1.5; extra == "runtime"
Requires-Dist: absl_py>=1.4.0; extra == "runtime"
Requires-Dist: PyYaml>=6.0.2; (python_version < "4.0" and python_version >= "3.13") and extra == "runtime"
Requires-Dist: PyYaml>=6.0.1; (python_version < "3.13" and python_version >= "3.12") and extra == "runtime"
Requires-Dist: PyYaml>=6.0; python_version < "3.12" and extra == "runtime"
Requires-Dist: tqdm>=4.64.1; extra == "runtime"
Requires-Dist: cmd_queue>=0.1.20; extra == "runtime"
Requires-Dist: fsspec>=2023.6.0; extra == "runtime"
Requires-Dist: s3fs>=2023.6.0; extra == "runtime"
Requires-Dist: portion>=2.4.1; extra == "runtime"
Requires-Dist: transformers>=4.37.2; extra == "runtime"
Provides-Extra: runtime-strict
Requires-Dist: numpy==2.1.0; (python_version < "4.0" and python_version >= "3.13") and extra == "runtime-strict"
Requires-Dist: numpy==1.26.0; (python_version < "3.13" and python_version >= "3.12") and extra == "runtime-strict"
Requires-Dist: numpy==1.23.2; (python_version < "3.12" and python_version >= "3.11") and extra == "runtime-strict"
Requires-Dist: numpy==1.23.2; (python_version < "3.11" and python_version >= "3.10") and extra == "runtime-strict"
Requires-Dist: scipy==1.14.1; (python_version < "4.0" and python_version >= "3.13") and extra == "runtime-strict"
Requires-Dist: scipy==1.11.2; (python_version < "3.13" and python_version >= "3.12") and extra == "runtime-strict"
Requires-Dist: scipy==1.9.2; (python_version < "3.12" and python_version >= "3.11") and extra == "runtime-strict"
Requires-Dist: scipy==1.8.0; (python_version < "3.11" and python_version >= "3.10") and extra == "runtime-strict"
Requires-Dist: shapely==2.0.6; (python_version < "4.0" and python_version >= "3.13") and extra == "runtime-strict"
Requires-Dist: shapely==2.0.2; (python_version < "3.13" and python_version >= "3.12") and extra == "runtime-strict"
Requires-Dist: shapely==2.0.1; (python_version < "3.12" and python_version >= "3.11") and extra == "runtime-strict"
Requires-Dist: shapely==2.0.1; (python_version < "3.11" and python_version >= "3.10") and extra == "runtime-strict"
Requires-Dist: rasterio==1.3.11; (python_version < "4.0" and python_version >= "3.13") and extra == "runtime-strict"
Requires-Dist: rasterio==1.3.9; (python_version < "3.13" and python_version >= "3.12") and extra == "runtime-strict"
Requires-Dist: rasterio==1.3.5; (python_version < "3.12" and python_version >= "3.11") and extra == "runtime-strict"
Requires-Dist: rasterio==1.3.5; (python_version < "3.11" and python_version >= "3.10") and extra == "runtime-strict"
Requires-Dist: pandas==2.2.3; (python_version < "4.0" and python_version >= "3.13") and extra == "runtime-strict"
Requires-Dist: pandas==2.1.1; (python_version < "3.13" and python_version >= "3.12") and extra == "runtime-strict"
Requires-Dist: pandas==1.5.3; (python_version < "3.12" and python_version >= "3.11") and extra == "runtime-strict"
Requires-Dist: pandas==1.5.3; (python_version < "3.11" and python_version >= "3.10") and extra == "runtime-strict"
Requires-Dist: scikit-learn==1.5.2; (python_version < "4.0" and python_version >= "3.13") and extra == "runtime-strict"
Requires-Dist: scikit-learn==1.3.1; (python_version < "3.13" and python_version >= "3.12") and extra == "runtime-strict"
Requires-Dist: scikit-learn==1.1.3; (python_version < "3.12" and python_version >= "3.11") and extra == "runtime-strict"
Requires-Dist: scikit-learn==1.1.0; (python_version < "3.11" and python_version >= "3.10") and extra == "runtime-strict"
Requires-Dist: scikit-image==0.25.1; (python_version < "4.0" and python_version >= "3.13") and extra == "runtime-strict"
Requires-Dist: scikit-image==0.22.0; (python_version < "3.13" and python_version >= "3.12") and extra == "runtime-strict"
Requires-Dist: scikit-image==0.20.0; (python_version < "3.12" and python_version >= "3.11") and extra == "runtime-strict"
Requires-Dist: scikit-image==0.19.0; (python_version < "3.11" and python_version >= "3.10") and extra == "runtime-strict"
Requires-Dist: jq==1.8.0; (python_version < "4.0" and python_version >= "3.13") and extra == "runtime-strict"
Requires-Dist: jq==1.7.0; (python_version < "3.13" and python_version >= "3.12") and extra == "runtime-strict"
Requires-Dist: jq==1.2.2; (python_version < "3.11" and python_version >= "3.10" and platform_system != "Windows") and extra == "runtime-strict"
Requires-Dist: jsonschema==4.19.2; extra == "runtime-strict"
Requires-Dist: pyproj==3.7.0; (python_version < "4.0" and python_version >= "3.13") and extra == "runtime-strict"
Requires-Dist: pyproj==3.6.1; (python_version < "3.13" and python_version >= "3.12") and extra == "runtime-strict"
Requires-Dist: pyproj<3.5.0,==3.4.1; (python_version < "3.12" and python_version >= "3.11") and extra == "runtime-strict"
Requires-Dist: pyproj<3.5.0,==3.3.1; (python_version < "3.11" and python_version >= "3.10") and extra == "runtime-strict"
Requires-Dist: fiona==1.10.0; (python_version < "4.0" and python_version >= "3.13") and extra == "runtime-strict"
Requires-Dist: fiona==1.9.5; (python_version < "3.13" and python_version >= "3.12") and extra == "runtime-strict"
Requires-Dist: fiona<1.9.0,==1.8.22; (python_version < "3.12" and python_version >= "3.11") and extra == "runtime-strict"
Requires-Dist: fiona<1.9.0,==1.8.22; (python_version < "3.11" and python_version >= "3.10") and extra == "runtime-strict"
Requires-Dist: matplotlib==3.9.2; (python_version < "4.0" and python_version >= "3.13") and extra == "runtime-strict"
Requires-Dist: matplotlib==3.8.2; (python_version < "3.13" and python_version >= "3.12") and extra == "runtime-strict"
Requires-Dist: matplotlib==3.8.2; (python_version < "3.12" and python_version >= "3.11") and extra == "runtime-strict"
Requires-Dist: matplotlib==3.8.2; (python_version < "3.11" and python_version >= "3.10") and extra == "runtime-strict"
Requires-Dist: Pillow==11.3.0; (python_version < "4.0" and python_version >= "3.13") and extra == "runtime-strict"
Requires-Dist: Pillow==10.2.0; python_version < "3.13" and extra == "runtime-strict"
Requires-Dist: psutil==5.9.6; (python_version < "4.0" and python_version >= "3.12") and extra == "runtime-strict"
Requires-Dist: psutil==5.9.6; (python_version < "3.12" and python_version >= "3.11") and extra == "runtime-strict"
Requires-Dist: psutil==5.9.6; (python_version < "3.11" and python_version >= "3.10") and extra == "runtime-strict"
Requires-Dist: rtree==1.2.0; python_version >= "3.11" and extra == "runtime-strict"
Requires-Dist: rtree==1.0.0; (python_version < "3.11" and python_version >= "3.10") and extra == "runtime-strict"
Requires-Dist: sqlalchemy==1.4.50; python_version >= "3.11" and extra == "runtime-strict"
Requires-Dist: sqlalchemy==1.4.37; (python_version < "3.11" and python_version >= "3.10") and extra == "runtime-strict"
Requires-Dist: xxhash==3.4.1; (python_version < "4.0" and python_version >= "3.12") and extra == "runtime-strict"
Requires-Dist: xxhash==3.4.1; (python_version < "3.12" and python_version >= "3.11") and extra == "runtime-strict"
Requires-Dist: xxhash==3.0.0; (python_version < "3.11" and python_version >= "3.10") and extra == "runtime-strict"
Requires-Dist: numexpr==2.10.2; (python_version < "4.0" and python_version >= "3.13") and extra == "runtime-strict"
Requires-Dist: numexpr==2.8.7; (python_version < "3.13" and python_version >= "3.12") and extra == "runtime-strict"
Requires-Dist: numexpr==2.8.4; (python_version < "3.12" and python_version >= "3.11") and extra == "runtime-strict"
Requires-Dist: numexpr==2.8.1; (python_version < "3.11" and python_version >= "3.10") and extra == "runtime-strict"
Requires-Dist: mgrs==1.4.6; (python_version < "4.0" and python_version >= "3.12") and extra == "runtime-strict"
Requires-Dist: mgrs==1.4.6; (python_version < "3.12" and python_version >= "3.11") and extra == "runtime-strict"
Requires-Dist: mgrs==1.4.3; (python_version < "3.11" and python_version >= "3.10") and extra == "runtime-strict"
Requires-Dist: kwarray==0.6.19; extra == "runtime-strict"
Requires-Dist: xarray==2023.10.0; extra == "runtime-strict"
Requires-Dist: einops==0.8.0; (python_version < "4.0" and python_version >= "3.13") and extra == "runtime-strict"
Requires-Dist: einops==0.6.0; python_version < "3.13" and extra == "runtime-strict"
Requires-Dist: dask[array]==2025.2.0; (python_version < "4.0" and python_version >= "3.13") and extra == "runtime-strict"
Requires-Dist: dask[array]==2023.5.0; python_version < "3.13" and extra == "runtime-strict"
Requires-Dist: rich==12.5.1; extra == "runtime-strict"
Requires-Dist: textual==0.1.18; extra == "runtime-strict"
Requires-Dist: text_unidecode==1.3; extra == "runtime-strict"
Requires-Dist: configargparse==1.7.1; extra == "runtime-strict"
Requires-Dist: parse==1.19.0; extra == "runtime-strict"
Requires-Dist: affine==2.3.0; extra == "runtime-strict"
Requires-Dist: ubelt==1.3.6; extra == "runtime-strict"
Requires-Dist: xmltodict==0.12.0; extra == "runtime-strict"
Requires-Dist: Pygments==2.12.0; extra == "runtime-strict"
Requires-Dist: requests==2.27.1; extra == "runtime-strict"
Requires-Dist: fasteners==0.17.3; extra == "runtime-strict"
Requires-Dist: kwutil==0.3.4; extra == "runtime-strict"
Requires-Dist: simple_dvc==0.2.1; extra == "runtime-strict"
Requires-Dist: blake3==1.0.1; (python_version < "4.0" and python_version >= "3.13") and extra == "runtime-strict"
Requires-Dist: blake3==1.0.1; (python_version < "3.13" and python_version >= "3.12") and extra == "runtime-strict"
Requires-Dist: blake3==0.3.1; (python_version < "3.12" and python_version >= "3.11") and extra == "runtime-strict"
Requires-Dist: blake3==0.2.1; python_version < "3.11" and extra == "runtime-strict"
Requires-Dist: more_itertools==8.12.0; extra == "runtime-strict"
Requires-Dist: pint==0.24.4; (python_version < "4.0" and python_version >= "3.13") and extra == "runtime-strict"
Requires-Dist: pint==0.23; python_version < "3.13" and extra == "runtime-strict"
Requires-Dist: girder_client==3.1.15; extra == "runtime-strict"
Requires-Dist: lxml==5.3.0; (python_version < "4.0" and python_version >= "3.11") and extra == "runtime-strict"
Requires-Dist: lxml==4.6.3; (python_version < "3.11" and python_version >= "3.10") and extra == "runtime-strict"
Requires-Dist: tempenv==0.2.0; extra == "runtime-strict"
Requires-Dist: pystac_client==0.5.1; extra == "runtime-strict"
Requires-Dist: scriptconfig==0.8.2; extra == "runtime-strict"
Requires-Dist: pygtrie==2.5.0; extra == "runtime-strict"
Requires-Dist: networkx==3.0.0; (python_version < "4.0" and python_version >= "3.13") and extra == "runtime-strict"
Requires-Dist: networkx==2.8.0; python_version < "3.12" and extra == "runtime-strict"
Requires-Dist: python_dateutil==2.8.2; extra == "runtime-strict"
Requires-Dist: pytimeparse==1.1.8; extra == "runtime-strict"
Requires-Dist: progiter==2.0.0; extra == "runtime-strict"
Requires-Dist: fire==0.4.0; extra == "runtime-strict"
Requires-Dist: lark==1.1.7; extra == "runtime-strict"
Requires-Dist: lark_cython==0.0.16; extra == "runtime-strict"
Requires-Dist: distinctipy==1.2.1; extra == "runtime-strict"
Requires-Dist: kwimage==0.11.2; extra == "runtime-strict"
Requires-Dist: kwcoco==0.8.5; extra == "runtime-strict"
Requires-Dist: kwcoco_dataloader==0.1.1; extra == "runtime-strict"
Requires-Dist: delayed_image==0.4.5; extra == "runtime-strict"
Requires-Dist: albumentations==1.0.0; extra == "runtime-strict"
Requires-Dist: ndsampler==0.8.0; extra == "runtime-strict"
Requires-Dist: tifffile==2022.8.12; (python_version < "4.0" and python_version >= "3.13") and extra == "runtime-strict"
Requires-Dist: tifffile==2021.4.8; python_version < "3.12" and extra == "runtime-strict"
Requires-Dist: kwplot==0.4.14; extra == "runtime-strict"
Requires-Dist: seaborn==0.13.0; extra == "runtime-strict"
Requires-Dist: kwgis==0.1.1; extra == "runtime-strict"
Requires-Dist: geopandas<1.0.0,==0.14.4; (python_version < "4.0" and python_version >= "3.13") and extra == "runtime-strict"
Requires-Dist: geopandas<1.0.0,==0.10.2; (python_version < "3.12" and python_version >= "3.8") and extra == "runtime-strict"
Requires-Dist: utm==0.7.0; extra == "runtime-strict"
Requires-Dist: rgd_imagery_client==0.2.7; extra == "runtime-strict"
Requires-Dist: rgd_client==0.2.7; extra == "runtime-strict"
Requires-Dist: geojson==3.1.0; (python_version < "4.0" and python_version >= "3.12") and extra == "runtime-strict"
Requires-Dist: geojson==3.0.1; (python_version < "3.12" and python_version >= "3.8") and extra == "runtime-strict"
Requires-Dist: torch==2.6.0; (python_version < "4.0" and python_version >= "3.13") and extra == "runtime-strict"
Requires-Dist: torch==2.2.0; (python_version < "3.13" and python_version >= "3.12") and extra == "runtime-strict"
Requires-Dist: torch==2.0.0; (python_version < "3.12" and python_version >= "3.11") and extra == "runtime-strict"
Requires-Dist: torch==1.12.0; python_version < "3.11" and extra == "runtime-strict"
Requires-Dist: torchvision==0.21.0; (python_version < "4.0" and python_version >= "3.13") and extra == "runtime-strict"
Requires-Dist: torchvision==0.17.0; (python_version < "3.13" and python_version >= "3.12") and extra == "runtime-strict"
Requires-Dist: torchvision==0.15.1; (python_version < "3.12" and python_version >= "3.11") and extra == "runtime-strict"
Requires-Dist: torchvision==0.13.0; python_version < "3.11" and extra == "runtime-strict"
Requires-Dist: torchmetrics==0.11.0; extra == "runtime-strict"
Requires-Dist: torch_liberator==0.2.1; extra == "runtime-strict"
Requires-Dist: omegaconf==2.3; extra == "runtime-strict"
Requires-Dist: hydra-core==1.3.2; extra == "runtime-strict"
Requires-Dist: jsonargparse[signatures]==4.19.0; extra == "runtime-strict"
Requires-Dist: pytorch_lightning!=2.3.*,!=2.4.0,==2.0.8; extra == "runtime-strict"
Requires-Dist: monai==1.3.2; (python_version < "4.0" and python_version >= "3.13") and extra == "runtime-strict"
Requires-Dist: monai==0.8.0; (python_version < "3.13" and python_version >= "3.11") and extra == "runtime-strict"
Requires-Dist: monai==0.6.0; python_version < "3.11" and extra == "runtime-strict"
Requires-Dist: torch_optimizer==0.1.0; extra == "runtime-strict"
Requires-Dist: timm<0.9.0,==0.6.13; (python_version < "4.0" and python_version >= "3.11") and extra == "runtime-strict"
Requires-Dist: timm<0.9.0,==0.4.12; python_version < "3.11" and extra == "runtime-strict"
Requires-Dist: kornia==0.6.8; extra == "runtime-strict"
Requires-Dist: segmentation-models-pytorch==0.2.0; python_version < "3.11" and extra == "runtime-strict"
Requires-Dist: ujson==5.6.0; (python_version < "4.0" and python_version >= "3.11") and extra == "runtime-strict"
Requires-Dist: ujson==5.2.0; python_version < "3.11" and extra == "runtime-strict"
Requires-Dist: kwimage_ext==0.2.1; (platform_system == "Linux" and python_version < "3.12") and extra == "runtime-strict"
Requires-Dist: py-cpuinfo==9.0.0; extra == "runtime-strict"
Requires-Dist: ruamel.yaml<=0.17.32,==0.17.22; extra == "runtime-strict"
Requires-Dist: ijson==3.2.1; (python_version < "4.0" and python_version >= "3.13") and extra == "runtime-strict"
Requires-Dist: ijson==3.2.1; (python_version < "3.13" and python_version >= "3.12") and extra == "runtime-strict"
Requires-Dist: ijson==3.2.1; (python_version < "3.12" and python_version >= "3.11") and extra == "runtime-strict"
Requires-Dist: ijson==3.2.1; (python_version < "3.11" and python_version >= "3.10") and extra == "runtime-strict"
Requires-Dist: lazy_loader==0.4; extra == "runtime-strict"
Requires-Dist: colormath==3.0.0; extra == "runtime-strict"
Requires-Dist: imagesize==1.4.1; extra == "runtime-strict"
Requires-Dist: pytorch_msssim==0.1.5; extra == "runtime-strict"
Requires-Dist: absl_py==1.4.0; extra == "runtime-strict"
Requires-Dist: PyYaml==6.0.2; (python_version < "4.0" and python_version >= "3.13") and extra == "runtime-strict"
Requires-Dist: PyYaml==6.0.1; (python_version < "3.13" and python_version >= "3.12") and extra == "runtime-strict"
Requires-Dist: PyYaml==6.0; python_version < "3.12" and extra == "runtime-strict"
Requires-Dist: tqdm==4.64.1; extra == "runtime-strict"
Requires-Dist: cmd_queue==0.1.20; extra == "runtime-strict"
Requires-Dist: fsspec==2023.6.0; extra == "runtime-strict"
Requires-Dist: s3fs==2023.6.0; extra == "runtime-strict"
Requires-Dist: portion==2.4.1; extra == "runtime-strict"
Requires-Dist: transformers==4.37.2; extra == "runtime-strict"
Provides-Extra: tensorflow
Requires-Dist: tensorflow>=2.12; extra == "tensorflow"
Requires-Dist: protobuf==3.20.3; extra == "tensorflow"
Provides-Extra: tensorflow-strict
Requires-Dist: tensorflow==2.12; extra == "tensorflow-strict"
Requires-Dist: protobuf==3.20.3; extra == "tensorflow-strict"
Provides-Extra: tests
Requires-Dist: pytest>=8.0.2; extra == "tests"
Requires-Dist: xdoctest>=1.1.5; extra == "tests"
Requires-Dist: pytest-cov>=3.0.0; extra == "tests"
Requires-Dist: coverage>=7.4.3; extra == "tests"
Requires-Dist: geodatasets>=2023.12.0; extra == "tests"
Provides-Extra: tests-strict
Requires-Dist: pytest==8.0.2; extra == "tests-strict"
Requires-Dist: xdoctest==1.1.5; extra == "tests-strict"
Requires-Dist: pytest-cov==3.0.0; extra == "tests-strict"
Requires-Dist: coverage==7.4.3; extra == "tests-strict"
Requires-Dist: geodatasets==2023.12.0; extra == "tests-strict"
Provides-Extra: graphics
Requires-Dist: opencv-python>=4.10.0.84; (python_version < "4.0" and python_version >= "3.13") and extra == "graphics"
Requires-Dist: opencv-python>=4.5.5.64; (python_version < "3.13" and python_version >= "3.11") and extra == "graphics"
Requires-Dist: opencv-python>=4.5.4.58; (python_version < "3.11" and python_version >= "3.10") and extra == "graphics"
Requires-Dist: opencv-python>=3.4.15.55; (python_version < "3.10" and python_version >= "3.10") and extra == "graphics"
Provides-Extra: graphics-strict
Requires-Dist: opencv-python==4.10.0.84; (python_version < "4.0" and python_version >= "3.13") and extra == "graphics-strict"
Requires-Dist: opencv-python==4.5.5.64; (python_version < "3.13" and python_version >= "3.11") and extra == "graphics-strict"
Requires-Dist: opencv-python==4.5.4.58; (python_version < "3.11" and python_version >= "3.10") and extra == "graphics-strict"
Requires-Dist: opencv-python==3.4.15.55; (python_version < "3.10" and python_version >= "3.10") and extra == "graphics-strict"
Provides-Extra: headless
Requires-Dist: opencv-python-headless>=4.10.0.84; (python_version < "4.0" and python_version >= "3.13") and extra == "headless"
Requires-Dist: opencv-python-headless>=4.5.5.64; (python_version < "3.13" and python_version >= "3.11") and extra == "headless"
Requires-Dist: opencv-python-headless>=4.5.4.58; (python_version < "3.11" and python_version >= "3.10") and extra == "headless"
Requires-Dist: opencv-python-headless>=3.4.15.55; (python_version < "3.10" and python_version >= "3.10") and extra == "headless"
Provides-Extra: headless-strict
Requires-Dist: opencv-python-headless==4.10.0.84; (python_version < "4.0" and python_version >= "3.13") and extra == "headless-strict"
Requires-Dist: opencv-python-headless==4.5.5.64; (python_version < "3.13" and python_version >= "3.11") and extra == "headless-strict"
Requires-Dist: opencv-python-headless==4.5.4.58; (python_version < "3.11" and python_version >= "3.10") and extra == "headless-strict"
Requires-Dist: opencv-python-headless==3.4.15.55; (python_version < "3.10" and python_version >= "3.10") and extra == "headless-strict"
Provides-Extra: compat
Requires-Dist: netharn>=0.6.1; extra == "compat"
Provides-Extra: compat-strict
Requires-Dist: netharn==0.6.1; extra == "compat-strict"
Dynamic: author
Dynamic: author-email
Dynamic: classifier
Dynamic: description
Dynamic: description-content-type
Dynamic: home-page
Dynamic: license
Dynamic: license-file
Dynamic: provides-extra
Dynamic: requires-dist
Dynamic: requires-python
